.gitignore
.travis.yml
CHANGELOG.rst
LICENSE
MANIFEST.in
README.rst
postBuild
readthedocs.yml
requirements.txt
setup.cfg
setup.py
docs/Makefile
docs/apigen.bash
docs/changelog.rst
docs/conf.py
docs/getting_started.rst
docs/index.rst
docs/installing.rst
docs/linkgalleries.rst
docs/requirements.txt
docs/api/sphinx_nbexamples.rst
examples/README.rst
examples/example_bash.ipynb
examples/example_basic.ipynb
examples/Subgallery/README.rst
examples/Subgallery/bokeh_example.png
examples/Subgallery/example_bokeh.ipynb
examples/images/bash.png
examples/images/select_metadata.png
sphinx_nbexamples/__init__.py
sphinx_nbexamples.egg-info/PKG-INFO
sphinx_nbexamples.egg-info/SOURCES.txt
sphinx_nbexamples.egg-info/dependency_links.txt
sphinx_nbexamples.egg-info/not-zip-safe
sphinx_nbexamples.egg-info/requires.txt
sphinx_nbexamples.egg-info/top_level.txt
sphinx_nbexamples/_static/example_gallery_styles.css
sphinx_nbexamples/_static/no_image.png
tests/test_sphinx_nbexamples.py
tests/sphinx_supp_py2/conf.py
tests/sphinx_supp_py2/index.rst
tests/sphinx_supp_py2/raw_examples/README.rst
tests/sphinx_supp_py2/raw_examples/example_bash.ipynb
tests/sphinx_supp_py2/raw_examples/example_code_example.ipynb
tests/sphinx_supp_py2/raw_examples/example_failure.ipynb
tests/sphinx_supp_py2/raw_examples/example_hello_world.ipynb
tests/sphinx_supp_py2/raw_examples/example_magics.ipynb
tests/sphinx_supp_py2/raw_examples/example_mpl_test.ipynb
tests/sphinx_supp_py2/raw_examples/example_mpl_test_figure_chosen.ipynb
tests/sphinx_supp_py2/raw_examples/example_tag_removal.ipynb
tests/sphinx_supp_py2/raw_examples/test2.txt
tests/sphinx_supp_py2/raw_examples/test_image.png
tests/sphinx_supp_py2/raw_examples/sub/README.md
tests/sphinx_supp_py2/raw_examples/sub/example_supplementary_files.ipynb
tests/sphinx_supp_py2/raw_examples/sub/example_toctree.ipynb
tests/sphinx_supp_py2/raw_examples/sub/test.txt
tests/sphinx_supp_py2/raw_examples/thumb/sphx_glr_test_image_thumb.png
tests/sphinx_supp_py3/conf.py
tests/sphinx_supp_py3/index.rst
tests/sphinx_supp_py3/raw_examples/README.rst
tests/sphinx_supp_py3/raw_examples/example_bash.ipynb
tests/sphinx_supp_py3/raw_examples/example_code_example.ipynb
tests/sphinx_supp_py3/raw_examples/example_failure.ipynb
