Metadata-Version: 2.1
Name: sphinx-nbexamples
Version: 0.4.1
Summary: Create an examples gallery with sphinx from Jupyter Notebooks
Home-page: https://github.com/Chilipp/sphinx-nbexamples
Author: Philipp S. Sommer
Author-email: philipp.sommer@hereon.de
License: MIT
Project-URL: Documentation, https://sphinx-nbexamples.readthedocs.io
Keywords: sphinx sphinx-gallery examples documentation notebook ipython jupyter nbconvert nbsphinx
Platform: UNKNOWN
Classifier: Development Status :: 7 - Inactive
Classifier: Intended Audience :: Developers
Classifier: Topic :: Documentation
Classifier: License :: OSI Approved :: GNU General Public License v2 (GPLv2)
Classifier: Programming Language :: Python :: 2
Classifier: Programming Language :: Python :: 2.7
Classifier: Programming Language :: Python :: 3
Classifier: Programming Language :: Python :: 3.2
Classifier: Programming Language :: Python :: 3.3
Classifier: Programming Language :: Python :: 3.4
Classifier: Programming Language :: Python :: 3.5
Classifier: Operating System :: OS Independent
